README.md
setup.py
hugo_deployer_git/__init__.py
hugo_deployer_git/check_env.py
hugo_deployer_git/deployer.py
hugo_deployer_git/fsutil.py
hugo_deployer_git.egg-info/PKG-INFO
hugo_deployer_git.egg-info/SOURCES.txt
hugo_deployer_git.egg-info/dependency_links.txt
hugo_deployer_git.egg-info/entry_points.txt
hugo_deployer_git.egg-info/requires.txt
hugo_deployer_git.egg-info/top_level.txt
hugo_deployer_git/cli/__init__.py
hugo_deployer_git/cli/__main__.py