Metadata-Version: 2.1
Name: hugo-deployer-git
Version: 0.0.4
Summary: Deploy your hugo site with github pages using one command
Home-page: https://github.com/ianre657/hugo-deployer-git
Author: Ian Chen
Author-email: ianre657@gmail.com
License: MIT
Keywords: hugo,github pages,deploy,git,blogger,utility,static site
Platform: UNKNOWN
Classifier: Programming Language :: Python :: 3
Classifier: License :: OSI Approved :: MIT License
Classifier: Operating System :: OS Independent
Classifier: Development Status :: 2 - Pre-Alpha
Classifier: Topic :: Utilities
